xy_django_app_feedback/__init__.py
xy_django_app_feedback/abstracts.py
xy_django_app_feedback/admin.py
xy_django_app_feedback/apps.py
xy_django_app_feedback/models.py
xy_django_app_feedback/serializers.py
xy_django_app_feedback/tests.py
xy_django_app_feedback/views.py
xy_django_app_feedback/migrations/__init__.py
xy_django_app_feedback-1.0.1.dist-info/LICENSE
xy_django_app_feedback-1.0.1.dist-info/METADATA
xy_django_app_feedback-1.0.1.dist-info/WHEEL
xy_django_app_feedback-1.0.1.dist-info/top_level.txt
xy_django_app_feedback-1.0.1.dist-info/RECORD
